{
  "assets": {
    "uris": {
      "jre-tar-gz": "https://downloads.mesosphere.com/java/jre-8u131-linux-x64.tar.gz",
      "libmesos-bundle-tar-gz": "https://downloads.mesosphere.com/libmesos-bundle/libmesos-bundle-1.9.0-rc2-1.2.0-rc2-1.tar.gz",
      "executor-zip": "https://downloads.mesosphere.com/elastic/assets/1.0.11-5.4.0-beta/executor.zip",
      "bootstrap-zip": "https://downloads.mesosphere.com/elastic/assets/1.0.11-5.4.0-beta/bootstrap.zip",
      "scheduler-zip": "https://downloads.mesosphere.com/elastic/assets/1.0.11-5.4.0-beta/elastic-scheduler.zip"
    }
  },
  "images": {
    "icon-small": "https://downloads.mesosphere.com/universe/assets/elasticsearch-small.png",
    "icon-medium": "https://downloads.mesosphere.com/universe/assets/elasticsearch-medium.png",
    "icon-large": "https://downloads.mesosphere.com/universe/assets/elasticsearch-large.png"
  },
  "cli": {
    "binaries": {
      "darwin": {
        "x86-64": {
          "contentHash": [
            {
              "algo": "sha256",
              "value": "7e1104a5ba9a5b4f9b00897d66daca680761bbb7bf5b44325c9a6564b2e52595"
            }
          ],
          "kind": "executable",
          "url": "https://downloads.mesosphere.com/elastic/assets/1.0.11-5.4.0-beta/dcos-elastic-darwin"
        }
      },
      "linux": {
        "x86-64": {
          "contentHash": [
            {
              "algo": "sha256",
              "value": "92f32e569d86e59794afdcdb9720bfc60b9b972b8c52b46a14a475c43a828d82"
            }
          ],
          "kind": "executable",
          "url": "https://downloads.mesosphere.com/elastic/assets/1.0.11-5.4.0-beta/dcos-elastic-linux"
        }
      },
      "windows": {
        "x86-64": {
          "contentHash": [
            {
              "algo": "sha256",
              "value": "9543d55f73cd650cffe17d5c97b483cc78414ff1f780338996040424173f44ca"
            }
          ],
          "kind": "executable",
          "url": "https://downloads.mesosphere.com/elastic/assets/1.0.11-5.4.0-beta/dcos-elastic.exe"
        }
      }
    }
  }
}
