{
  "assets": {
    "uris": {
      "jre-tar-gz": "https://downloads.mesosphere.com/java/jre-8u131-linux-x64.tar.gz",
      "libmesos-bundle-tar-gz": "https://downloads.mesosphere.com/libmesos-bundle/libmesos-bundle-1.9.0-rc2-1.2.0-rc2-1.tar.gz",
      "executor-zip": "https://downloads.mesosphere.com/elastic/assets/1.0.13-5.4.1-beta/executor.zip",
      "bootstrap-zip": "https://downloads.mesosphere.com/elastic/assets/1.0.13-5.4.1-beta/bootstrap.zip",
      "scheduler-zip": "https://downloads.mesosphere.com/elastic/assets/1.0.13-5.4.1-beta/elastic-scheduler.zip",
      "statsd-plugin-zip": "https://github.com/mesosphere/elasticsearch-statsd-plugin/releases/download/5.4.1.0/elasticsearch-statsd-5.4.1.0.zip",
      "elasticsearch-tar-gz": "https://artifacts.elastic.co/downloads/elasticsearch/elasticsearch-5.4.1.tar.gz",
      "xpack-zip": "https://artifacts.elastic.co/downloads/packs/x-pack/x-pack-5.4.1.zip",
      "diagnostics-zip": "https://github.com/elastic/elasticsearch-support-diagnostics/releases/download/5.12/support-diagnostics-5.12-dist.zip"
    }
  },
  "images": {
    "icon-small": "https://downloads.mesosphere.com/universe/assets/elasticsearch-small.png",
    "icon-medium": "https://downloads.mesosphere.com/universe/assets/elasticsearch-medium.png",
    "icon-large": "https://downloads.mesosphere.com/universe/assets/elasticsearch-large.png"
  },
  "cli": {
    "binaries": {
      "darwin": {
        "x86-64": {
          "contentHash": [
            {
              "algo": "sha256",
              "value": "6b61522f801178041be82c18aa9470f2107022ce4b6d16bd5768d5355f4939a0"
            }
          ],
          "kind": "executable",
          "url": "https://downloads.mesosphere.com/elastic/assets/1.0.13-5.4.1-beta/dcos-elastic-darwin"
        }
      },
      "linux": {
        "x86-64": {
          "contentHash": [
            {
              "algo": "sha256",
              "value": "45c144bd5dc9a635fe55bbe6ab72109433342f2370158690f1594e0c9fa3e67c"
            }
          ],
          "kind": "executable",
          "url": "https://downloads.mesosphere.com/elastic/assets/1.0.13-5.4.1-beta/dcos-elastic-linux"
        }
      },
      "windows": {
        "x86-64": {
          "contentHash": [
            {
              "algo": "sha256",
              "value": "5daa99ce50cc910cb31c8662ca962022e3560b395ed83065624647d7f6d69ff0"
            }
          ],
          "kind": "executable",
          "url": "https://downloads.mesosphere.com/elastic/assets/1.0.13-5.4.1-beta/dcos-elastic.exe"
        }
      }
    }
  }
}
